[
    {
        "date":"20260518",
        "unyo":"久留米 - 大牟田線①京",
        "bus_no":"2425"
    },
    {
        "date":"20260518",
        "unyo":"香椎線①舞",
        "bus_no":"2602"
    },
    {
        "date":"20260518",
        "unyo":"門司 - 戸畑線①門",
        "bus_no":"2711"
    },
    {
        "date":"20260518",
        "unyo":"福岡?熊本線⑳高T",
        "bus_no":"2768"
    },
    {
        "date":"20260518",
        "unyo":"大橋?福翔線③那",
        "bus_no":"2775"
    },
    {
        "date":"20260518",
        "unyo":"門司 - 戸畑線③門",
        "bus_no":"2832"
    },
    {
        "date":"20260518",
        "unyo":"門司 - 戸畑線⑤門",
        "bus_no":"2834"
    },
    {
        "date":"20260518",
        "unyo":"福重（都市高速）線①壱",
        "bus_no":"2937"
    },
    {
        "date":"20260518",
        "unyo":"那珂川フィーダー線②那",
        "bus_no":"2963"
    },
    {
        "date":"20260518",
        "unyo":"大里線①恒",
        "bus_no":"2971"
    },
    {
        "date":"20260518",
        "unyo":"今町・若園線①谷",
        "bus_no":"2979"
    },
    {
        "date":"20260518",
        "unyo":"小倉 - 黒崎・折尾線①幡",
        "bus_no":"1050"
    },
    {
        "date":"20260518",
        "unyo":"小倉～北九州空港線①北",
        "bus_no":"1078"
    },
    {
        "date":"20260518",
        "unyo":"小倉 - 黒崎線①幡",
        "bus_no":"1161"
    },
    {
        "date":"20260518",
        "unyo":"長野 - 小倉線①弥",
        "bus_no":"1189"
    },
    {
        "date":"20260518",
        "unyo":"大橋?福翔線②那",
        "bus_no":"1297"
    },
    {
        "date":"20260518",
        "unyo":"恒見 - 小倉線⑲恒T",
        "bus_no":"1308"
    },
    {
        "date":"20260518",
        "unyo":"福岡空港-久留米線①京",
        "bus_no":"1332"
    },
    {
        "date":"20260518",
        "unyo":"福岡?鹿児島線①高T",
        "bus_no":"1336"
    },
    {
        "date":"20260518",
        "unyo":"宇美線③宇",
        "bus_no":"1803"
    },
    {
        "date":"20260518",
        "unyo":"野間快速線①桧",
        "bus_no":"3660"
    },
    {
        "date":"20260518",
        "unyo":"福岡～小倉線②博",
        "bus_no":"4855"
    },
    {
        "date":"20260518",
        "unyo":"福岡・福岡空港?日田線①日",
        "bus_no":"4878"
    },
    {
        "date":"20260518",
        "unyo":"福岡・福岡空港～佐世保線②博T",
        "bus_no":"3284"
    },
    {
        "date":"20260518",
        "unyo":"小倉～北九州空港線⑧北T",
        "bus_no":"3286"
    },
    {
        "date":"20260518",
        "unyo":"福岡～小倉線②北",
        "bus_no":"3434"
    },
    {
        "date":"20260518",
        "unyo":"久留米吉井線①吉",
        "bus_no":"5884"
    },
    {
        "date":"20260518",
        "unyo":"志井線①谷",
        "bus_no":"9016"
    },
    {
        "date":"20260518",
        "unyo":"小嶺 - 戸畑・若松線②香",
        "bus_no":"9021"
    },
    {
        "date":"20260518",
        "unyo":"小嶺 - 戸畑・若松線①香",
        "bus_no":"9022"
    },
    {
        "date":"20260518",
        "unyo":"門司 - 戸畑線①戸",
        "bus_no":"9086"
    },
    {
        "date":"20260518",
        "unyo":"黒崎・戸畑 - 砂津線①幡",
        "bus_no":"9232"
    },
    {
        "date":"20260518",
        "unyo":"屋形原線①那",
        "bus_no":"9311"
    },
    {
        "date":"20260518",
        "unyo":"香椎浜～博多駅線⑪アT",
        "bus_no":"9324"
    },
    {
        "date":"20260518",
        "unyo":"小倉 - 黒崎・折尾線②幡",
        "bus_no":"9351"
    },
    {
        "date":"20260518",
        "unyo":"野方（都市高速）博多線④壱",
        "bus_no":"9811"
    },
    {
        "date":"20260518",
        "unyo":"諸岡線①竹",
        "bus_no":"9844"
    },
    {
        "date":"20260518",
        "unyo":"小倉（中原）戸畑線③小T",
        "bus_no":"9894"
    },
    {
        "date":"20260518",
        "unyo":"黒原 - 戸畑線①弥",
        "bus_no":"5905"
    },
    {
        "date":"20260518",
        "unyo":"筑豊（特急）福岡線①田",
        "bus_no":"5981"
    },
    {
        "date":"20260518",
        "unyo":"屋形原線②那",
        "bus_no":"5689"
    },
    {
        "date":"20260518",
        "unyo":"門司 - 戸畑線②門",
        "bus_no":"5769"
    },
    {
        "date":"20260518",
        "unyo":"国分線①御",
        "bus_no":"8534"
    },
    {
        "date":"20260518",
        "unyo":"那珂川フィーダー線①那",
        "bus_no":"7715"
    },
    {
        "date":"20260518",
        "unyo":"大野城市循環バス線①月",
        "bus_no":"23"
    },
    {
        "date":"20260518",
        "unyo":"大野城市循環バス線②月",
        "bus_no":"027"
    },
    {
        "date":"20260518",
        "unyo":"甘木幹線⑤杷T",
        "bus_no":"2010"
    },
    {
        "date":"20260518",
        "unyo":"南福岡線⑤宇T",
        "bus_no":"2103"
    },
    {
        "date":"20260518",
        "unyo":"四王寺坂線①宇",
        "bus_no":"2106"
    },
    {
        "date":"20260518",
        "unyo":"春日原線②那",
        "bus_no":"2108"
    },
    {
        "date":"20260518",
        "unyo":"春日原線③那",
        "bus_no":"2109"
    },
    {
        "date":"20260518",
        "unyo":"那珂川フィーダー線⑤那",
        "bus_no":"2110"
    },
    {
        "date":"20260518",
        "unyo":"直方?鞍手?遠賀線①直",
        "bus_no":"2113"
    },
    {
        "date":"20260518",
        "unyo":"甘木幹線①杷",
        "bus_no":"2130"
    },
    {
        "date":"20260518",
        "unyo":"沖新線①川",
        "bus_no":"2264"
    },
    {
        "date":"20260518",
        "unyo":"吉野線④牟",
        "bus_no":"2266"
    },
    {
        "date":"20260518",
        "unyo":"星ヶ丘線①原",
        "bus_no":"2267"
    },
    {
        "date":"20260518",
        "unyo":"春日原線①月",
        "bus_no":"2403"
    },
    {
        "date":"20260518",
        "unyo":"竹下～長浜線①も",
        "bus_no":"2412"
    },
    {
        "date":"20260518",
        "unyo":"竹下～長浜線②も",
        "bus_no":"2413"
    },
    {
        "date":"20260518",
        "unyo":"竹下～長浜線③も",
        "bus_no":"2420"
    },
    {
        "date":"20260518",
        "unyo":"直方 ・ 黒崎線③直T",
        "bus_no":"2422"
    },
    {
        "date":"20260518",
        "unyo":"久留米 - 鳥栖線①鳥",
        "bus_no":"2430"
    },
    {
        "date":"20260518",
        "unyo":"天拝坂線①原T",
        "bus_no":"2431"
    },
    {
        "date":"20260518",
        "unyo":"上官（大牟田）線①牟",
        "bus_no":"2511"
    },
    {
        "date":"20260518",
        "unyo":"則松循環線①香",
        "bus_no":"2519"
    },
    {
        "date":"20260518",
        "unyo":"小嶺 - 戸畑・若松線①戸",
        "bus_no":"2524"
    },
    {
        "date":"20260518",
        "unyo":"多々良・八田線①土",
        "bus_no":"2535"
    },
    {
        "date":"20260518",
        "unyo":"志賀島線②ア",
        "bus_no":"2603"
    },
    {
        "date":"20260518",
        "unyo":"香椎浜～博多駅線①ア",
        "bus_no":"2604"
    },
    {
        "date":"20260518",
        "unyo":"甘木幹線②甘",
        "bus_no":"2607"
    },
    {
        "date":"20260518",
        "unyo":"南福岡線②宇",
        "bus_no":"2609"
    },
    {
        "date":"20260518",
        "unyo":"小倉 - 黒崎・折尾線③小",
        "bus_no":"2616"
    },
    {
        "date":"20260518",
        "unyo":"小笹・小笹団地線①柏",
        "bus_no":"2663"
    },
    {
        "date":"20260518",
        "unyo":"赤間（普通）線①高",
        "bus_no":"2665"
    },
    {
        "date":"20260518",
        "unyo":"姪浜フィーダー線④壱",
        "bus_no":"2666"
    },
    {
        "date":"20260518",
        "unyo":"竹下～長浜線②竹",
        "bus_no":"2676"
    },
    {
        "date":"20260518",
        "unyo":"大橋?福翔線⑨那",
        "bus_no":"2681"
    },
    {
        "date":"20260518",
        "unyo":"大橋?福翔線⑪那",
        "bus_no":"2684"
    },
    {
        "date":"20260518",
        "unyo":"飯塚市内線⑤飯",
        "bus_no":"2689"
    },
    {
        "date":"20260518",
        "unyo":"飯塚市内線①飯",
        "bus_no":"2698"
    },
    {
        "date":"20260518",
        "unyo":"北野線①御",
        "bus_no":"2699"
    },
    {
        "date":"20260518",
        "unyo":"霧丘 - 小倉駅線①小",
        "bus_no":"2710"
    },
    {
        "date":"20260518",
        "unyo":"門司 - 戸畑線⑪門",
        "bus_no":"2712"
    },
    {
        "date":"20260518",
        "unyo":"金武（城南）博多駅線①武",
        "bus_no":"2726"
    },
    {
        "date":"20260518",
        "unyo":"西新（城南）九大線②愛",
        "bus_no":"2731"
    },
    {
        "date":"20260518",
        "unyo":"屋形原線⑤那",
        "bus_no":"2736"
    },
    {
        "date":"20260518",
        "unyo":"屋形原線⑥那",
        "bus_no":"2738"
    },
    {
        "date":"20260518",
        "unyo":"大橋?福翔線⑱那",
        "bus_no":"2739"
    },
    {
        "date":"20260518",
        "unyo":"西団地 - 萩原線①幡",
        "bus_no":"2747"
    },
    {
        "date":"20260518",
        "unyo":"蒲生線①谷",
        "bus_no":"2748"
    },
    {
        "date":"20260518",
        "unyo":"大谷線・大谷（大蔵）線②戸",
        "bus_no":"2751"
    },
    {
        "date":"20260518",
        "unyo":"門司 - 戸畑線⑦門",
        "bus_no":"2757"
    },
    {
        "date":"20260518",
        "unyo":"黒原 - 戸畑線②戸",
        "bus_no":"2761"
    },
    {
        "date":"20260518",
        "unyo":"黒原 - 戸畑線①戸",
        "bus_no":"2764"
    },
    {
        "date":"20260518",
        "unyo":"福岡?熊本線④高",
        "bus_no":"2769"
    },
    {
        "date":"20260518",
        "unyo":"渡辺通幹線①も",
        "bus_no":"2771"
    },
    {
        "date":"20260518",
        "unyo":"渡辺通幹線③那",
        "bus_no":"2779"
    },
    {
        "date":"20260518",
        "unyo":"渡辺通幹線④那",
        "bus_no":"2788"
    },
    {
        "date":"20260518",
        "unyo":"野間（城南）博多駅線①桧",
        "bus_no":"2793"
    },
    {
        "date":"20260518",
        "unyo":"玄海～東郷線①赤",
        "bus_no":"2799"
    },
    {
        "date":"20260518",
        "unyo":"脇山線⑥早",
        "bus_no":"2803"
    },
    {
        "date":"20260518",
        "unyo":"門司駅～山田線②谷",
        "bus_no":"2835"
    },
    {
        "date":"20260518",
        "unyo":"門司駅～山田線③谷",
        "bus_no":"2836"
    },
    {
        "date":"20260518",
        "unyo":"西団地 - 萩原線②幡",
        "bus_no":"2850"
    },
    {
        "date":"20260518",
        "unyo":"小嶺 - 戸畑・若松線⑤香",
        "bus_no":"2854"
    },
    {
        "date":"20260518",
        "unyo":"馬場山～大平線③香",
        "bus_no":"2855"
    },
    {
        "date":"20260518",
        "unyo":"馬場山～大平線②香",
        "bus_no":"2856"
    },
    {
        "date":"20260518",
        "unyo":"上山田線①飯",
        "bus_no":"2866"
    },
    {
        "date":"20260518",
        "unyo":"飯塚 - 大隈線①飯",
        "bus_no":"2868"
    },
    {
        "date":"20260518",
        "unyo":"脇山支線①早",
        "bus_no":"2869"
    },
    {
        "date":"20260518",
        "unyo":"古賀市内線①舞",
        "bus_no":"2871"
    },
    {
        "date":"20260518",
        "unyo":"門司駅～山田線①谷",
        "bus_no":"2906"
    },
    {
        "date":"20260518",
        "unyo":"門司駅～山田線⑤谷",
        "bus_no":"2907"
    },
    {
        "date":"20260518",
        "unyo":"板付線③竹",
        "bus_no":"2918"
    },
    {
        "date":"20260518",
        "unyo":"竹下～長浜線①竹",
        "bus_no":"2922"
    },
    {
        "date":"20260518",
        "unyo":"片江（長住）博多駅線③片",
        "bus_no":"2925"
    },
    {
        "date":"20260518",
        "unyo":"那珂川フィーダー線⑥那",
        "bus_no":"2932"
    },
    {
        "date":"20260518",
        "unyo":"大谷線・大谷（大蔵）線①戸",
        "bus_no":"2938"
    },
    {
        "date":"20260518",
        "unyo":"福岡・福岡空港～佐世保線④博T",
        "bus_no":"2976"
    },
    {
        "date":"20260518",
        "unyo":"大谷線・大谷（大蔵）線③戸",
        "bus_no":"2977"
    },
    {
        "date":"20260518",
        "unyo":"今町・若園線③谷",
        "bus_no":"2980"
    },
    {
        "date":"20260518",
        "unyo":"西新（城南）九大線②塚",
        "bus_no":"1022"
    },
    {
        "date":"20260518",
        "unyo":"昭代（城南）博多駅線①愛",
        "bus_no":"1030"
    },
    {
        "date":"20260518",
        "unyo":"志賀島線①ア",
        "bus_no":"1039"
    },
    {
        "date":"20260518",
        "unyo":"宇美線⑰宇",
        "bus_no":"1040"
    },
    {
        "date":"20260518",
        "unyo":"宇美線①宇",
        "bus_no":"1043"
    },
    {
        "date":"20260518",
        "unyo":"恒見 - 小倉線⑥恒",
        "bus_no":"1048"
    },
    {
        "date":"20260518",
        "unyo":"志井線④谷",
        "bus_no":"1052"
    },
    {
        "date":"20260518",
        "unyo":"門司 - 戸畑線④戸",
        "bus_no":"1071"
    },
    {
        "date":"20260518",
        "unyo":"福岡?熊本線①高",
        "bus_no":"1080"
    },
    {
        "date":"20260518",
        "unyo":"福岡?熊本線(22)高T",
        "bus_no":"1082"
    },
    {
        "date":"20260518",
        "unyo":"西新（城南）九大線①塚",
        "bus_no":"1093"
    },
    {
        "date":"20260518",
        "unyo":"小倉（中原）戸畑線④戸",
        "bus_no":"1104"
    },
    {
        "date":"20260518",
        "unyo":"折尾 - 小嶺線①香",
        "bus_no":"1107"
    },
    {
        "date":"20260518",
        "unyo":"門司 - 戸畑線③戸",
        "bus_no":"1157"
    },
    {
        "date":"20260518",
        "unyo":"小嶺 - 戸畑・若松線③香",
        "bus_no":"1159"
    },
    {
        "date":"20260518",
        "unyo":"志井線⑤谷",
        "bus_no":"1163"
    },
    {
        "date":"20260518",
        "unyo":"福岡?熊本線③高",
        "bus_no":"1167"
    },
    {
        "date":"20260518",
        "unyo":"馬場山～大平線①香",
        "bus_no":"1192"
    },
    {
        "date":"20260518",
        "unyo":"門司港ローカル線①門",
        "bus_no":"1239"
    },
    {
        "date":"20260518",
        "unyo":"渡辺通幹線②那",
        "bus_no":"1254"
    },
    {
        "date":"20260518",
        "unyo":"渡辺通幹線①那",
        "bus_no":"1255"
    },
    {
        "date":"20260518",
        "unyo":"渡辺通幹線⑨那",
        "bus_no":"1256"
    },
    {
        "date":"20260518",
        "unyo":"西新（城南）九大線①愛",
        "bus_no":"1261"
    },
    {
        "date":"20260518",
        "unyo":"宇美線②宇",
        "bus_no":"1265"
    },
    {
        "date":"20260518",
        "unyo":"竹下～長浜線②も",
        "bus_no":"1266"
    },
    {
        "date":"20260518",
        "unyo":"油山線①片",
        "bus_no":"1267"
    },
    {
        "date":"20260518",
        "unyo":"小倉 - 黒崎・折尾線④小T",
        "bus_no":"1277"
    },
    {
        "date":"20260518",
        "unyo":"恒見 - 小倉線②恒",
        "bus_no":"1279"
    },
    {
        "date":"20260518",
        "unyo":"香椎浜～博多駅線②ア",
        "bus_no":"1293"
    },
    {
        "date":"20260518",
        "unyo":"香椎浜～天神線①ア",
        "bus_no":"1294"
    },
    {
        "date":"20260518",
        "unyo":"黒崎・戸畑 - 砂津線③小",
        "bus_no":"1304"
    },
    {
        "date":"20260518",
        "unyo":"福岡～宮崎線⑧高T",
        "bus_no":"1337"
    },
    {
        "date":"20260518",
        "unyo":"西新（城南）九大線②も",
        "bus_no":"1340"
    },
    {
        "date":"20260518",
        "unyo":"大橋?福翔線⑤那",
        "bus_no":"1348"
    },
    {
        "date":"20260518",
        "unyo":"貫 (都市高速) 小倉線①弥",
        "bus_no":"1354"
    },
    {
        "date":"20260518",
        "unyo":"荒江線①早",
        "bus_no":"1451"
    },
    {
        "date":"20260518",
        "unyo":"多々良・八田線⑤土",
        "bus_no":"1459"
    },
    {
        "date":"20260518",
        "unyo":"大橋?福翔線⑩那",
        "bus_no":"1808"
    },
    {
        "date":"20260518",
        "unyo":"大橋?福翔線⑫那",
        "bus_no":"1809"
    },
    {
        "date":"20260518",
        "unyo":"みどりヶ丘線②土",
        "bus_no":"1820"
    },
    {
        "date":"20260518",
        "unyo":"みどりヶ丘線③土",
        "bus_no":"1821"
    },
    {
        "date":"20260518",
        "unyo":"多々良・八田線②土",
        "bus_no":"1822"
    },
    {
        "date":"20260518",
        "unyo":"那珂川フィーダー線⑨那",
        "bus_no":"1915"
    },
    {
        "date":"20260518",
        "unyo":"脇山線①博",
        "bus_no":"1921"
    },
    {
        "date":"20260518",
        "unyo":"志賀島島内線①ア",
        "bus_no":"1923"
    },
    {
        "date":"20260518",
        "unyo":"脇山線②早",
        "bus_no":"4605"
    },
    {
        "date":"20260518",
        "unyo":"野間快速線②桧",
        "bus_no":"4609"
    },
    {
        "date":"20260518",
        "unyo":"恒見 - 小倉線①恒",
        "bus_no":"4611"
    },
    {
        "date":"20260518",
        "unyo":"門司 - 戸畑線①恒",
        "bus_no":"4612"
    },
    {
        "date":"20260518",
        "unyo":"黒原 - 戸畑線⑧弥T",
        "bus_no":"4616"
    },
    {
        "date":"20260518",
        "unyo":"新八田線①土",
        "bus_no":"3633"
    },
    {
        "date":"20260518",
        "unyo":"志賀島線④ア",
        "bus_no":"3644"
    },
    {
        "date":"20260518",
        "unyo":"赤間（普通）線②高",
        "bus_no":"3647"
    },
    {
        "date":"20260518",
        "unyo":"野間快速線⑧桧",
        "bus_no":"3658"
    },
    {
        "date":"20260518",
        "unyo":"片江（長住）博多駅線①片",
        "bus_no":"3662"
    },
    {
        "date":"20260518",
        "unyo":"筑豊（特急）福岡線⑤田",
        "bus_no":"4705"
    },
    {
        "date":"20260518",
        "unyo":"筑豊（特急）福岡線②飯",
        "bus_no":"4706"
    },
    {
        "date":"20260518",
        "unyo":"筑豊（特急）福岡線②田",
        "bus_no":"4722"
    },
    {
        "date":"20260518",
        "unyo":"三軒屋線②武",
        "bus_no":"4832"
    },
    {
        "date":"20260518",
        "unyo":"金武（城南）博多駅線②武",
        "bus_no":"4833"
    },
    {
        "date":"20260518",
        "unyo":"宇美線④宇",
        "bus_no":"4844"
    },
    {
        "date":"20260518",
        "unyo":"空港循環線⑤宇T",
        "bus_no":"4845"
    },
    {
        "date":"20260518",
        "unyo":"佐賀?福岡線①博",
        "bus_no":"4856"
    },
    {
        "date":"20260518",
        "unyo":"香椎線③ア",
        "bus_no":"4864"
    },
    {
        "date":"20260518",
        "unyo":"野間～天神線④柏",
        "bus_no":"4870"
    },
    {
        "date":"20260518",
        "unyo":"小笹・小笹団地線⑭柏",
        "bus_no":"4871"
    },
    {
        "date":"20260518",
        "unyo":"福岡～小倉線③博",
        "bus_no":"4905"
    },
    {
        "date":"20260518",
        "unyo":"福岡～小倉線①博",
        "bus_no":"4907"
    },
    {
        "date":"20260518",
        "unyo":"早良（城南）博多駅①早",
        "bus_no":"4915"
    },
    {
        "date":"20260518",
        "unyo":"宇美線⑦宇",
        "bus_no":"4920"
    },
    {
        "date":"20260518",
        "unyo":"宇美線⑧宇",
        "bus_no":"4922"
    },
    {
        "date":"20260518",
        "unyo":"野間～天神線①柏",
        "bus_no":"4924"
    },
    {
        "date":"20260518",
        "unyo":"小笹・小笹団地線②柏",
        "bus_no":"4925"
    },
    {
        "date":"20260518",
        "unyo":"野間～天神線③桧",
        "bus_no":"4927"
    },
    {
        "date":"20260518",
        "unyo":"早良（城南）博多駅⑦早",
        "bus_no":"4933"
    },
    {
        "date":"20260518",
        "unyo":"片江（長住）博多駅線②片",
        "bus_no":"4941"
    },
    {
        "date":"20260518",
        "unyo":"福岡～小倉線④博",
        "bus_no":"3016"
    },
    {
        "date":"20260518",
        "unyo":"福岡～小倉線④北",
        "bus_no":"3019"
    },
    {
        "date":"20260518",
        "unyo":"福岡～小倉線⑧北",
        "bus_no":"3021"
    },
    {
        "date":"20260518",
        "unyo":"貫 (都市高速) 小倉線②弥",
        "bus_no":"3025"
    },
    {
        "date":"20260518",
        "unyo":"油山線①桧",
        "bus_no":"3037"
    },
    {
        "date":"20260518",
        "unyo":"筑豊（特急）福岡線①飯",
        "bus_no":"3046"
    },
    {
        "date":"20260518",
        "unyo":"小笹・小笹団地線⑰柏",
        "bus_no":"3059"
    },
    {
        "date":"20260518",
        "unyo":"宇美線⑫宇",
        "bus_no":"3066"
    },
    {
        "date":"20260518",
        "unyo":"野間快速線①柏",
        "bus_no":"3222"
    },
    {
        "date":"20260518",
        "unyo":"長住?博多駅線①桧",
        "bus_no":"3271"
    },
    {
        "date":"20260518",
        "unyo":"油山（快速）博多駅線③桧T",
        "bus_no":"3272"
    },
    {
        "date":"20260518",
        "unyo":"福岡・福岡空港～佐世保線③博T",
        "bus_no":"3282"
    },
    {
        "date":"20260518",
        "unyo":"片江（城南）博多駅線①片",
        "bus_no":"3295"
    },
    {
        "date":"20260518",
        "unyo":"福岡～小倉線⑤北",
        "bus_no":"3331"
    },
    {
        "date":"20260518",
        "unyo":"三軒屋線①武",
        "bus_no":"3423"
    },
    {
        "date":"20260518",
        "unyo":"宇美線⑥宇",
        "bus_no":"3430"
    },
    {
        "date":"20260518",
        "unyo":"坂瀬線①宇",
        "bus_no":"3433"
    },
    {
        "date":"20260518",
        "unyo":"福岡～小倉線③北",
        "bus_no":"3435"
    },
    {
        "date":"20260518",
        "unyo":"福岡～小倉線⑥北",
        "bus_no":"3439"
    },
    {
        "date":"20260518",
        "unyo":"野間快速線②柏",
        "bus_no":"3709"
    },
    {
        "date":"20260518",
        "unyo":"板付線①竹",
        "bus_no":"5824"
    },
    {
        "date":"20260518",
        "unyo":"小倉（中原）戸畑線②戸",
        "bus_no":"5829"
    },
    {
        "date":"20260518",
        "unyo":"昭代（城南）博多駅線②愛",
        "bus_no":"5834"
    },
    {
        "date":"20260518",
        "unyo":"二日市線②原",
        "bus_no":"5850"
    },
    {
        "date":"20260518",
        "unyo":"小笹?天神線①片",
        "bus_no":"5857"
    },
    {
        "date":"20260518",
        "unyo":"久留米吉井線④吉",
        "bus_no":"5859"
    },
    {
        "date":"20260518",
        "unyo":"久留米吉井線③吉",
        "bus_no":"5861"
    },
    {
        "date":"20260518",
        "unyo":"赤間（普通）線①赤",
        "bus_no":"5879"
    },
    {
        "date":"20260518",
        "unyo":"甘木（都市高速）博多駅線⑮甘T",
        "bus_no":"5891"
    },
    {
        "date":"20260518",
        "unyo":"福島線③八",
        "bus_no":"5893"
    },
    {
        "date":"20260518",
        "unyo":"西新（城南）九大線①も",
        "bus_no":"5898"
    },
    {
        "date":"20260518",
        "unyo":"津屋崎～福間線①赤",
        "bus_no":"9006"
    },
    {
        "date":"20260518",
        "unyo":"津屋崎～福間線③赤",
        "bus_no":"9007"
    },
    {
        "date":"20260518",
        "unyo":"志井線⑦谷",
        "bus_no":"9011"
    },
    {
        "date":"20260518",
        "unyo":"小倉（中原）戸畑線①弥",
        "bus_no":"9014"
    },
    {
        "date":"20260518",
        "unyo":"志井線②谷",
        "bus_no":"9017"
    },
    {
        "date":"20260518",
        "unyo":"志井線③谷",
        "bus_no":"9018"
    },
    {
        "date":"20260518",
        "unyo":"志井線⑥谷",
        "bus_no":"9024"
    },
    {
        "date":"20260518",
        "unyo":"姪浜フィーダー線①壱",
        "bus_no":"9029"
    },
    {
        "date":"20260518",
        "unyo":"屋形原線⑫那",
        "bus_no":"9030"
    },
    {
        "date":"20260518",
        "unyo":"屋形原線④那",
        "bus_no":"9054"
    },
    {
        "date":"20260518",
        "unyo":"久留米吉井線②吉",
        "bus_no":"9057"
    },
    {
        "date":"20260518",
        "unyo":"馬場山～大平線⑨香",
        "bus_no":"9058"
    },
    {
        "date":"20260518",
        "unyo":"南ヶ丘線①月",
        "bus_no":"9061"
    },
    {
        "date":"20260518",
        "unyo":"甘木（都市高速）博多駅線①甘",
        "bus_no":"9063"
    },
    {
        "date":"20260518",
        "unyo":"甘木幹線④甘",
        "bus_no":"9064"
    },
    {
        "date":"20260518",
        "unyo":"荒江線②早",
        "bus_no":"9068"
    },
    {
        "date":"20260518",
        "unyo":"福大線①片",
        "bus_no":"9079"
    },
    {
        "date":"20260518",
        "unyo":"久留米市内線①御",
        "bus_no":"9081"
    },
    {
        "date":"20260518",
        "unyo":"飯塚市内線②飯",
        "bus_no":"9084"
    },
    {
        "date":"20260518",
        "unyo":"小嶺 - 戸畑・若松線④香",
        "bus_no":"9089"
    },
    {
        "date":"20260518",
        "unyo":"馬場山～大平線⑫香T",
        "bus_no":"9090"
    },
    {
        "date":"20260518",
        "unyo":"片江（城南）博多駅線②片",
        "bus_no":"9093"
    },
    {
        "date":"20260518",
        "unyo":"久留米市内線①京",
        "bus_no":"9101"
    },
    {
        "date":"20260518",
        "unyo":"赤間（普通）線②赤",
        "bus_no":"9118"
    },
    {
        "date":"20260518",
        "unyo":"森林都市線②赤",
        "bus_no":"9121"
    },
    {
        "date":"20260518",
        "unyo":"南福岡線①竹",
        "bus_no":"9122"
    },
    {
        "date":"20260518",
        "unyo":"春日原線①那",
        "bus_no":"9127"
    },
    {
        "date":"20260518",
        "unyo":"昭代?天神線①壱",
        "bus_no":"9137"
    },
    {
        "date":"20260518",
        "unyo":"板付団地線①竹",
        "bus_no":"9138"
    },
    {
        "date":"20260518",
        "unyo":"空港循環線①宇",
        "bus_no":"9210"
    },
    {
        "date":"20260518",
        "unyo":"篠栗線（篠）①土",
        "bus_no":"9214"
    },
    {
        "date":"20260518",
        "unyo":"久留米 - 大牟田線②京",
        "bus_no":"9220"
    },
    {
        "date":"20260518",
        "unyo":"小倉 - 黒崎・折尾線④幡",
        "bus_no":"9221"
    },
    {
        "date":"20260518",
        "unyo":"黒原 - 戸畑線①小",
        "bus_no":"9222"
    },
    {
        "date":"20260518",
        "unyo":"小倉 - 黒崎線②幡",
        "bus_no":"9231"
    },
    {
        "date":"20260518",
        "unyo":"黒崎・戸畑 - 砂津線③幡",
        "bus_no":"9235"
    },
    {
        "date":"20260518",
        "unyo":"黒崎・戸畑 - 砂津線②幡",
        "bus_no":"9236"
    },
    {
        "date":"20260518",
        "unyo":"黒原 - 戸畑線⑨弥T",
        "bus_no":"9238"
    },
    {
        "date":"20260518",
        "unyo":"春日?大橋線①那",
        "bus_no":"9263"
    },
    {
        "date":"20260518",
        "unyo":"脇山線⑤早",
        "bus_no":"9266"
    },
    {
        "date":"20260518",
        "unyo":"南ヶ丘線②月",
        "bus_no":"9267"
    },
    {
        "date":"20260518",
        "unyo":"福島線①八",
        "bus_no":"9269"
    },
    {
        "date":"20260518",
        "unyo":"多々良・八田線③土",
        "bus_no":"9274"
    },
    {
        "date":"20260518",
        "unyo":"須恵線④宇T",
        "bus_no":"9279"
    },
    {
        "date":"20260518",
        "unyo":"福島線②八",
        "bus_no":"9283"
    },
    {
        "date":"20260518",
        "unyo":"佐賀 - 柳川線①川",
        "bus_no":"9285"
    },
    {
        "date":"20260518",
        "unyo":"久留米 - 大牟田線③京",
        "bus_no":"9287"
    },
    {
        "date":"20260518",
        "unyo":"甘木幹線①甘",
        "bus_no":"9297"
    },
    {
        "date":"20260518",
        "unyo":"博多駅?西新線②も",
        "bus_no":"9309"
    },
    {
        "date":"20260518",
        "unyo":"香椎浜～博多駅線④ア",
        "bus_no":"9321"
    },
    {
        "date":"20260518",
        "unyo":"多々良・八田線⑥土",
        "bus_no":"9322"
    },
    {
        "date":"20260518",
        "unyo":"つつじヶ丘線②月",
        "bus_no":"9323"
    },
    {
        "date":"20260518",
        "unyo":"福島線⑩八",
        "bus_no":"9332"
    },
    {
        "date":"20260518",
        "unyo":"福島線⑥八",
        "bus_no":"9346"
    },
    {
        "date":"20260518",
        "unyo":"小倉 - 黒崎・折尾線⑥小T",
        "bus_no":"9353"
    },
    {
        "date":"20260518",
        "unyo":"屋形原線⑮那",
        "bus_no":"9375"
    },
    {
        "date":"20260518",
        "unyo":"小倉 - 黒崎・折尾線⑦幡",
        "bus_no":"9413"
    },
    {
        "date":"20260518",
        "unyo":"福島線④八",
        "bus_no":"9429"
    },
    {
        "date":"20260518",
        "unyo":"小倉 - 黒崎・折尾線⑤幡",
        "bus_no":"9433"
    },
    {
        "date":"20260518",
        "unyo":"金武線①塚",
        "bus_no":"9434"
    },
    {
        "date":"20260518",
        "unyo":"博多駅?西新線①博",
        "bus_no":"9435"
    },
    {
        "date":"20260518",
        "unyo":"小倉 - 黒崎線④小T",
        "bus_no":"9451"
    },
    {
        "date":"20260518",
        "unyo":"小倉 - 黒崎線⑥幡",
        "bus_no":"9454"
    },
    {
        "date":"20260518",
        "unyo":"脇山線③早",
        "bus_no":"9455"
    },
    {
        "date":"20260518",
        "unyo":"早良（城南）博多駅③早",
        "bus_no":"9456"
    },
    {
        "date":"20260518",
        "unyo":"那珂川フィーダー線④那",
        "bus_no":"9463"
    },
    {
        "date":"20260518",
        "unyo":"森林都市線①赤",
        "bus_no":"9468"
    },
    {
        "date":"20260518",
        "unyo":"小倉 - 黒崎・折尾線⑦小T",
        "bus_no":"9490"
    },
    {
        "date":"20260518",
        "unyo":"小倉 - 黒崎・折尾線③幡",
        "bus_no":"9492"
    },
    {
        "date":"20260518",
        "unyo":"屋形原線⑦那",
        "bus_no":"9499"
    },
    {
        "date":"20260518",
        "unyo":"香椎線②ア",
        "bus_no":"9520"
    },
    {
        "date":"20260518",
        "unyo":"小笹・小笹団地線④柏",
        "bus_no":"9645"
    },
    {
        "date":"20260518",
        "unyo":"国分線③御",
        "bus_no":"9653"
    },
    {
        "date":"20260518",
        "unyo":"シーサイドももち線⑦愛",
        "bus_no":"9664"
    },
    {
        "date":"20260518",
        "unyo":"諸岡線④竹",
        "bus_no":"9670"
    },
    {
        "date":"20260518",
        "unyo":"屋形原線③那",
        "bus_no":"9682"
    },
    {
        "date":"20260518",
        "unyo":"門司 - 戸畑線②戸",
        "bus_no":"9687"
    },
    {
        "date":"20260518",
        "unyo":"黒原 - 戸畑線⑧戸",
        "bus_no":"9688"
    },
    {
        "date":"20260518",
        "unyo":"森林都市線③赤",
        "bus_no":"9809"
    },
    {
        "date":"20260518",
        "unyo":"赤間（普通）線③赤",
        "bus_no":"9810"
    },
    {
        "date":"20260518",
        "unyo":"諸岡線③竹",
        "bus_no":"9815"
    },
    {
        "date":"20260518",
        "unyo":"新八田線②土",
        "bus_no":"9816"
    },
    {
        "date":"20260518",
        "unyo":"みどりヶ丘線⑤土",
        "bus_no":"9818"
    },
    {
        "date":"20260518",
        "unyo":"坂瀬線②宇",
        "bus_no":"9827"
    },
    {
        "date":"20260518",
        "unyo":"博多駅?西新線①塚",
        "bus_no":"9831"
    },
    {
        "date":"20260518",
        "unyo":"早良（城南）博多駅④早",
        "bus_no":"9848"
    },
    {
        "date":"20260518",
        "unyo":"みどりヶ丘線①土",
        "bus_no":"9869"
    },
    {
        "date":"20260518",
        "unyo":"金武線②武",
        "bus_no":"9878"
    },
    {
        "date":"20260518",
        "unyo":"那珂川フィーダー線⑰那T",
        "bus_no":"9886"
    },
    {
        "date":"20260518",
        "unyo":"小倉（中原）戸畑線④小T",
        "bus_no":"9895"
    },
    {
        "date":"20260518",
        "unyo":"黒崎・戸畑 - 砂津線①小",
        "bus_no":"9900"
    },
    {
        "date":"20260518",
        "unyo":"恒見 - 小倉線③恒",
        "bus_no":"9901"
    },
    {
        "date":"20260518",
        "unyo":"小倉 - 黒崎線③幡",
        "bus_no":"9943"
    },
    {
        "date":"20260518",
        "unyo":"黒原 - 戸畑線③弥",
        "bus_no":"9955"
    },
    {
        "date":"20260518",
        "unyo":"大里線②恒",
        "bus_no":"9958"
    },
    {
        "date":"20260518",
        "unyo":"小倉 - 黒崎・折尾線⑤小T",
        "bus_no":"5901"
    },
    {
        "date":"20260518",
        "unyo":"鞘ヶ谷 - 大谷池線①小",
        "bus_no":"5906"
    },
    {
        "date":"20260518",
        "unyo":"小倉 - 黒崎・折尾線①小",
        "bus_no":"5907"
    },
    {
        "date":"20260518",
        "unyo":"小倉 - 黒崎線④幡",
        "bus_no":"5909"
    },
    {
        "date":"20260518",
        "unyo":"小倉 - 黒崎・折尾線⑧幡",
        "bus_no":"5910"
    },
    {
        "date":"20260518",
        "unyo":"門司 - 戸畑線⑥門",
        "bus_no":"5913"
    },
    {
        "date":"20260518",
        "unyo":"黒原 - 戸畑線②弥",
        "bus_no":"5914"
    },
    {
        "date":"20260518",
        "unyo":"つつじヶ丘線①月",
        "bus_no":"5923"
    },
    {
        "date":"20260518",
        "unyo":"アイランドシティ～千早線①ア",
        "bus_no":"5927"
    },
    {
        "date":"20260518",
        "unyo":"昭代（城南）博多駅線②塚",
        "bus_no":"5929"
    },
    {
        "date":"20260518",
        "unyo":"西新（城南）九大線③塚",
        "bus_no":"5930"
    },
    {
        "date":"20260518",
        "unyo":"森林都市線④赤",
        "bus_no":"5931"
    },
    {
        "date":"20260518",
        "unyo":"金武線①壱",
        "bus_no":"5941"
    },
    {
        "date":"20260518",
        "unyo":"シーサイドももち線⑤愛",
        "bus_no":"5953"
    },
    {
        "date":"20260518",
        "unyo":"黒原 - 戸畑線⑤弥",
        "bus_no":"5961"
    },
    {
        "date":"20260518",
        "unyo":"野方（都市高速）博多線⑤壱",
        "bus_no":"5965"
    },
    {
        "date":"20260518",
        "unyo":"諸岡線②竹",
        "bus_no":"5977"
    },
    {
        "date":"20260518",
        "unyo":"坂瀬線⑫宇T",
        "bus_no":"5987"
    },
    {
        "date":"20260518",
        "unyo":"福重（都市高速）線②壱",
        "bus_no":"6000"
    },
    {
        "date":"20260518",
        "unyo":"鞘ヶ谷 - 大谷池線④小",
        "bus_no":"6004"
    },
    {
        "date":"20260518",
        "unyo":"鞘ヶ谷 - 大谷池線③小",
        "bus_no":"6005"
    },
    {
        "date":"20260518",
        "unyo":"小倉（中原）戸畑線③戸",
        "bus_no":"6006"
    },
    {
        "date":"20260518",
        "unyo":"黒原 - 戸畑線③戸",
        "bus_no":"6007"
    },
    {
        "date":"20260518",
        "unyo":"恒見 - 小倉線⑳恒T",
        "bus_no":"6012"
    },
    {
        "date":"20260518",
        "unyo":"福岡?熊本線②高",
        "bus_no":"6102"
    },
    {
        "date":"20260518",
        "unyo":"黒崎北九州空港線①幡T",
        "bus_no":"6108"
    },
    {
        "date":"20260518",
        "unyo":"赤間（急行）福岡線①舞",
        "bus_no":"6110"
    },
    {
        "date":"20260518",
        "unyo":"赤間（急行）福岡線①赤",
        "bus_no":"6115"
    },
    {
        "date":"20260518",
        "unyo":"筑豊（特急）福岡線④田",
        "bus_no":"6119"
    },
    {
        "date":"20260518",
        "unyo":"シーサイドももち線②愛",
        "bus_no":"6121"
    },
    {
        "date":"20260518",
        "unyo":"野間快速線③柏",
        "bus_no":"6131"
    },
    {
        "date":"20260518",
        "unyo":"黒原 - 戸畑線④弥",
        "bus_no":"6144"
    },
    {
        "date":"20260518",
        "unyo":"門司 - 戸畑線⑥戸",
        "bus_no":"6148"
    },
    {
        "date":"20260518",
        "unyo":"黒原 - 戸畑線④戸",
        "bus_no":"6151"
    },
    {
        "date":"20260518",
        "unyo":"鞘ヶ谷 - 大谷池線⑧小T",
        "bus_no":"6153"
    },
    {
        "date":"20260518",
        "unyo":"昭代（城南）博多駅線①も",
        "bus_no":"6156"
    },
    {
        "date":"20260518",
        "unyo":"タワー（天神）貝塚線①も",
        "bus_no":"6157"
    },
    {
        "date":"20260518",
        "unyo":"諸岡線⑤竹",
        "bus_no":"6158"
    },
    {
        "date":"20260518",
        "unyo":"金武線①武",
        "bus_no":"6159"
    },
    {
        "date":"20260518",
        "unyo":"桧原（小笹）博多駅線①博",
        "bus_no":"6169"
    },
    {
        "date":"20260518",
        "unyo":"国分線②御",
        "bus_no":"6176"
    },
    {
        "date":"20260518",
        "unyo":"屋形原線⑲那",
        "bus_no":"6184"
    },
    {
        "date":"20260518",
        "unyo":"屋形原線⑭那",
        "bus_no":"6197"
    },
    {
        "date":"20260518",
        "unyo":"門司 - 戸畑線⑭戸T",
        "bus_no":"6211"
    },
    {
        "date":"20260518",
        "unyo":"小倉 - 黒崎・折尾線②小",
        "bus_no":"6224"
    },
    {
        "date":"20260518",
        "unyo":"茶山線①片",
        "bus_no":"6236"
    },
    {
        "date":"20260518",
        "unyo":"香椎線①ア",
        "bus_no":"6244"
    },
    {
        "date":"20260518",
        "unyo":"小倉（中原）戸畑線①戸",
        "bus_no":"5775"
    },
    {
        "date":"20260518",
        "unyo":"綾部線①鳥",
        "bus_no":"8004"
    },
    {
        "date":"20260518",
        "unyo":"朽網?北九州空港線①弥",
        "bus_no":"8009"
    },
    {
        "date":"20260518",
        "unyo":"綾部線②鳥",
        "bus_no":"8050"
    },
    {
        "date":"20260518",
        "unyo":"野間～天神線⑩桧",
        "bus_no":"8016"
    },
    {
        "date":"20260518",
        "unyo":"吉野線①牟",
        "bus_no":"8404"
    },
    {
        "date":"20260518",
        "unyo":"米の山・黒崎団地線①牟",
        "bus_no":"8405"
    },
    {
        "date":"20260518",
        "unyo":"門司 - 戸畑線④門",
        "bus_no":"8507"
    },
    {
        "date":"20260518",
        "unyo":"二日市線③原",
        "bus_no":"8512"
    },
    {
        "date":"20260518",
        "unyo":"飯塚 - 大隈線②飯",
        "bus_no":"8518"
    },
    {
        "date":"20260518",
        "unyo":"二日市線①原",
        "bus_no":"8520"
    },
    {
        "date":"20260518",
        "unyo":"長野 - 小倉線②弥",
        "bus_no":"8525"
    },
    {
        "date":"20260518",
        "unyo":"野間～天神線②柏",
        "bus_no":"8543"
    },
    {
        "date":"20260518",
        "unyo":"門司 - 戸畑線⑧門",
        "bus_no":"8606"
    },
    {
        "date":"20260518",
        "unyo":"福岡?熊本線(21)高T",
        "bus_no":"7611"
    },
    {
        "date":"20260518",
        "unyo":"脇山線①早",
        "bus_no":"7703"
    },
    {
        "date":"20260518",
        "unyo":"香椎線②舞",
        "bus_no":"7710"
    },
    {
        "date":"20260518",
        "unyo":"西新（城南）九大線④愛",
        "bus_no":"7727"
    },
    {
        "date":"20260518",
        "unyo":"野間（城南）博多駅線⑧桧T",
        "bus_no":"7732"
    },
    {
        "date":"20260518",
        "unyo":"門司 - 戸畑線(26)門T",
        "bus_no":"7743"
    },
    {
        "date":"20260518",
        "unyo":"脇山線(38)早T",
        "bus_no":"7804"
    },
    {
        "date":"20260518",
        "unyo":"野間～天神線②桧",
        "bus_no":"7807"
    },
    {
        "date":"20260518",
        "unyo":"野方（都市高速）博多線③壱",
        "bus_no":"7812"
    },
    {
        "date":"20260518",
        "unyo":"甘木（都市高速）博多駅線②甘",
        "bus_no":"7828"
    },
    {
        "date":"20260518",
        "unyo":"赤間（急行）福岡線⑪赤T",
        "bus_no":"7829"
    },
    {
        "date":"20260518",
        "unyo":"太宰府市役所循環線①原",
        "bus_no":"7832"
    },
    {
        "date":"20260518",
        "unyo":"長住?天神線①桧",
        "bus_no":"7835"
    },
    {
        "date":"20260518",
        "unyo":"長住?天神線②桧",
        "bus_no":"7839"
    },
    {
        "date":"20260518",
        "unyo":"赤間（急行）福岡線②赤",
        "bus_no":"8019"
    },
    {
        "date":"20260518",
        "unyo":"長住?博多駅線②桧",
        "bus_no":"8025"
    },
    {
        "date":"20260518",
        "unyo":"香椎浜～博多駅線③ア",
        "bus_no":"8105"
    },
    {
        "date":"20260518",
        "unyo":"大橋?福翔線①那",
        "bus_no":"8109"
    },
    {
        "date":"20260518",
        "unyo":"大橋?福翔線④那",
        "bus_no":"8111"
    },
    {
        "date":"20260518",
        "unyo":"油山（快速）博多駅線②片",
        "bus_no":"8127"
    },
    {
        "date":"20260518",
        "unyo":"佐賀?福岡線②佐",
        "bus_no":"8131"
    },
    {
        "date":"20260518",
        "unyo":"那珂川フィーダー線③那",
        "bus_no":"8134"
    },
    {
        "date":"20260518",
        "unyo":"野間～天神線④桧",
        "bus_no":"8204"
    },
    {
        "date":"20260518",
        "unyo":"野間～天神線③柏",
        "bus_no":"8207"
    },
    {
        "date":"20260518",
        "unyo":"野間～天神線①桧",
        "bus_no":"8210"
    },
    {
        "date":"20260518",
        "unyo":"野方（都市高速）博多線①壱",
        "bus_no":"8213"
    },
    {
        "date":"20260518",
        "unyo":"福大病院（外環状）線①片",
        "bus_no":"8222"
    },
    {
        "date":"20260518",
        "unyo":"タワー（天神）貝塚線①塚",
        "bus_no":"8302"
    },
    {
        "date":"20260518",
        "unyo":"昭代（城南）博多駅線①塚",
        "bus_no":"8303"
    },
    {
        "date":"20260518",
        "unyo":"油山線⑤片",
        "bus_no":"8310"
    },
    {
        "date":"20260518",
        "unyo":"佐賀?福岡線①佐",
        "bus_no":"8314"
    },
    {
        "date":"20260518",
        "unyo":"福岡～小倉線⑦北",
        "bus_no":"8316"
    },
    {
        "date":"20260518",
        "unyo":"片江（城南）博多駅線③片",
        "bus_no":"8423"
    },
    {
        "date":"20260518",
        "unyo":"板付団地線②竹",
        "bus_no":"8432"
    },
    {
        "date":"20260518",
        "unyo":"福岡空港-久留米線②京",
        "bus_no":"8436"
    },
    {
        "date":"20260518",
        "unyo":"山路・猪倉線①小",
        "bus_no":"8557"
    },
    {
        "date":"20260518",
        "unyo":"奥田線①恒",
        "bus_no":"8654"
    },
    {
        "date":"20260518",
        "unyo":"恒見フィーダー線①恒",
        "bus_no":"8751"
    },
    {
        "date":"20260518",
        "unyo":"竹末線①香",
        "bus_no":"8752"
    },
    {
        "date":"20260518",
        "unyo":"野方（都市高速）博多線②壱",
        "bus_no":"8801"
    },
    {
        "date":"20260518",
        "unyo":"福重（都市高速）線(22)壱T",
        "bus_no":"8802"
    },
    {
        "date":"20260518",
        "unyo":"長住?博多駅線③桧",
        "bus_no":"8808"
    },
    {
        "date":"20260518",
        "unyo":"福大病院（外環状）線②片",
        "bus_no":"8810"
    }
]